data_dashboard/__init__.py
data_dashboard/analyzer.py
data_dashboard/dashboard.py
data_dashboard/descriptor.py
data_dashboard/features.py
data_dashboard/functions.py
data_dashboard/model_finder.py
data_dashboard/models.py
data_dashboard/output.py
data_dashboard/plot_design.py
data_dashboard/plots.py
data_dashboard/transformer.py
data_dashboard/views.py
data_dashboard/examples/__init__.py
data_dashboard/examples/examples.py
data_dashboard/static/features.css
data_dashboard/static/features.js
data_dashboard/static/models.css
data_dashboard/static/models.js
data_dashboard/static/overview.css
data_dashboard/static/style.css
data_dashboard/templates/base.html
data_dashboard/templates/features.html
data_dashboard/templates/models.html
data_dashboard/templates/overview.html
data_dashboard-0.1.1.dist-info/LICENSE
data_dashboard-0.1.1.dist-info/METADATA
data_dashboard-0.1.1.dist-info/WHEEL
data_dashboard-0.1.1.dist-info/top_level.txt
data_dashboard-0.1.1.dist-info/RECORD
